Metadata-Version: 1.0
Name: distributions-families
Version: 0.1
Summary: Gaussian and binomial distributions
Home-page: UNKNOWN
Author: Asmaa Elbasioni
Author-email: a.elbasioni@gmail.com
License: UNKNOWN
Platform: UNKNOWN
